AUTHORS
CHANGES.txt
LICENCE.txt
MANIFEST.in
README.txt
setup.py
pySSSO/__init__.py
pySSSO.egg-info/PKG-INFO
pySSSO.egg-info/SOURCES.txt
pySSSO.egg-info/dependency_links.txt
pySSSO.egg-info/requires.txt
pySSSO.egg-info/top_level.txt
pySSSO/fsrc/__init__.py
pySSSO/ioUtils/__init__.py
pySSSO/ioUtils/binFileManipulation.py
pySSSO/ioUtils/ncFileManipulation_class.py
pySSSO/ioUtils/subLatLonMod.py
pySSSO/stationPlottingTool/._plotStation_class.py
pySSSO/stationPlottingTool/._wxStationPlotGUI.py
pySSSO/stationPlottingTool/__init__.py
pySSSO/stationPlottingTool/annoteFinderClass.py
pySSSO/stationPlottingTool/plotStationClass.py
pySSSO/stationPlottingTool/wxPlotStationGUI.py
pySSSO/tests/__init__.py
pySSSO/tests/datetime_increment.py
pySSSO/tests/extractDataFromFile.py
pySSSO/tests/from_template_to_filename.py
pySSSO/tests/getJan2004_metfields_list.py
pySSSO/tests/myListFile.py
pySSSO/tests/ncRead_WriteMean.py
pySSSO/tests/ncWriting.py
pySSSO/tests/timeSeriesPlots.py
pySSSO/utils/GCE_radar_plot.py
pySSSO/utils/__init__.py
pySSSO/utils/date_time_control.py
pySSSO/utils/generate_metfields_list.py
pySSSO/utils/listDistPackages.py
pySSSO/utils/massPassiveTracers.py
pySSSO/utils/massPassiveTracers_CO.py
pySSSO/utils/massPassiveTracers_CTM.py
pySSSO/utils/module_av_filter.py
pySSSO/utils/nc4Files_identical_pyScript.py
pySSSO/utils/nc4Files_xxdiff_pyScript.py
pySSSO/utils/nc4Files_xxdiff_pyScriptGMI.py
pySSSO/utils/stats_functions.py
pySSSO/utils/template_to_name.py
pySSSO/viz/__init__.py
pySSSO/viz/bmUtilities.py
pySSSO/viz/cartUtilities.py
pySSSO/viz/mplibUtilities.py
pySSSO/viz/palette_chl_etc.txt
pySSSO/viz/plotUtilities.py
pySSSO/viz/registerColormaps.py
pySSSO/viz/row_cols_decomp.py
pySSSO/viz/vertLevels_GEOS5.py