Metadata-Version: 1.0
Name: pySSSO
Version: 1.0.0
Summary: Useful script to manipulate data and visualize them.
Home-page: https://pypi.python.org/pypi/pySSSO/
Author: Jules Kouatchou
Author-email: Jules.Kouatchou-1@nasa.gov
License: LICENSE.txt
Platform: UNKNOWN
